smls/__init__.py
smls/api_key.py
smls/constants.py
smls/seamless.py
smls/example_job/__init__.py
smls/example_job/function.py
smls/example_job/requirements.txt
tests/__init__.py
tests/integration/__init__.py
tests/integration/conftest.py
tests/integration/test_cli_interface.py
tests/unit/__init__.py
tests/unit/test_publish_command.py
smls-0.0.19.dist-info/LICENSE.txt
smls-0.0.19.dist-info/METADATA
smls-0.0.19.dist-info/WHEEL
smls-0.0.19.dist-info/entry_points.txt
smls-0.0.19.dist-info/top_level.txt
smls-0.0.19.dist-info/RECORD
