Metadata-Version: 2.1
Name: smls
Version: 0.0.19
Summary: Command Line Interface to work with the Seamless Cloud product
Home-page: https://github.com/https://github.com/seamless-io/seamless-cli
Author: Seamless Cloud
Author-email: hello@seamlesscloud.io
License: ISC
Platform: UNKNOWN
Classifier: License :: OSI Approved :: ISC License (ISCL)
Classifier: Programming Language :: Python :: 3
Classifier: Programming Language :: Python :: 3.6
Classifier: Programming Language :: Python :: 3.7
Classifier: Programming Language :: Python :: 3.8
Requires-Dist: setuptools-git
Requires-Dist: click (~=7.1.2)
Requires-Dist: requests (~=2.23.0)
Requires-Dist: responses (~=0.10.15)
